pyutgenerator/__init__.py
pyutgenerator/ast_util.py
pyutgenerator/code_analysis.py
pyutgenerator/const.py
pyutgenerator/files.py
pyutgenerator/objects.py
pyutgenerator/run.py
pyutgenerator/templates.py
pyutgenerator-0.12.0.dist-info/entry_points.txt
pyutgenerator-0.12.0.dist-info/LICENSE
pyutgenerator-0.12.0.dist-info/WHEEL
pyutgenerator-0.12.0.dist-info/METADATA
pyutgenerator-0.12.0.dist-info/RECORD
