Metadata-Version: 2.1
Name: pyutgenerator
Version: 0.12.0
Summary: python ut test code generator.
Home-page: https://py-ut-generator.readthedocs.io/en/latest/
License: MIT
Author: shigeshige
Author-email: 5540474+shigeshige@users.noreply.github.com
Requires-Python: >=3.7,<4.0
Classifier: License :: OSI Approved :: MIT License
Classifier: Programming Language :: Python :: 3
Classifier: Programming Language :: Python :: 3.10
Classifier: Programming Language :: Python :: 3.7
Classifier: Programming Language :: Python :: 3.8
Classifier: Programming Language :: Python :: 3.9
Project-URL: Repository, https://github.com/shigeshige/py-ut-generator
